{
  "version": 1,
  "createdAt": "2026-05-06T11:57:48.924269+00:00",
  "source": "output/production-73-rollout-pages.json + output/build-production-83-scope.log",
  "summary": {
    "checkedUrls": 83,
    "http200": 83,
    "byDecision": {
      "strengthen_seo": 81,
      "review_noindex_or_rename_slug": 2
    },
    "byIssue": {
      "images_missing_alt": 83,
      "missing_jsonld": 82,
      "missing_h1": 43,
      "multiple_h1": 14,
      "duplicate_description": 4,
      "duplicate_title": 2,
      "opaque_or_test_slug": 2,
      "canonical_mismatch": 1,
      "long_title": 1
    },
    "byKind": {
      "home": 1,
      "other": 31,
      "article": 13,
      "knowledge_base": 16,
      "lecture_or_events": 5,
      "service": 15,
      "test_or_staging": 2
    },
    "groups": {
      "strengthen_seo": [
        "https://moonn.ru/",
        "https://moonn.ru/abuse_gaslight",
        "https://moonn.ru/aromatherapy",
        "https://moonn.ru/article_diary_of_emotions",
        "https://moonn.ru/article_femininity",
        "https://moonn.ru/article_gadget_addiction",
        "https://moonn.ru/article_toxic_job",
        "https://moonn.ru/articles/eq-dlya-rukovoditeley",
        "https://moonn.ru/baza-znaniy-emocionalnyy-intellekt-psihologiya",
        "https://moonn.ru/eintellect",
        "https://moonn.ru/emotional-intelligence/",
        "https://moonn.ru/emotional-intelligence/articles",
        "https://moonn.ru/emotional-intelligence/articles/benefits-of-ei",
        "https://moonn.ru/emotional-intelligence/articles/emotional-intelligence-skills",
        "https://moonn.ru/emotional-intelligence/articles/what-is-emotional-intelligence",
        "https://moonn.ru/emotional-intelligence/articles/why-ei-matters",
        "https://moonn.ru/emotional-intelligence/diagnostoka-ei",
        "https://moonn.ru/emotional-intelligence/ei-leader-12",
        "https://moonn.ru/emotional-intelligence/knowledge-base",
        "https://moonn.ru/emotional-intelligence/knowledge-base/active-listening",
        "https://moonn.ru/emotional-intelligence/knowledge-base/burnout",
        "https://moonn.ru/emotional-intelligence/knowledge-base/emotional-contagion",
        "https://moonn.ru/emotional-intelligence/knowledge-base/emotional-intelligence",
        "https://moonn.ru/emotional-intelligence/knowledge-base/emotional-literacy",
        "https://moonn.ru/emotional-intelligence/knowledge-base/emotional-maturity",
        "https://moonn.ru/emotional-intelligence/knowledge-base/empathy",
        "https://moonn.ru/emotional-intelligence/knowledge-base/intrinsic-motivation",
        "https://moonn.ru/emotional-intelligence/knowledge-base/male-loneliness-russia",
        "https://moonn.ru/emotional-intelligence/knowledge-base/nonviolent-communication",
        "https://moonn.ru/emotional-intelligence/knowledge-base/personal-boundaries",
        "https://moonn.ru/emotional-intelligence/knowledge-base/psychological-safety",
        "https://moonn.ru/emotional-intelligence/knowledge-base/self-awareness",
        "https://moonn.ru/emotional-intelligence/knowledge-base/self-regulation",
        "https://moonn.ru/emotional-intelligence/knowledge-base/social-intelligence",
        "https://moonn.ru/events",
        "https://moonn.ru/events_tp",
        "https://moonn.ru/geshtalt",
        "https://moonn.ru/kpt",
        "https://moonn.ru/kurs-ei",
        "https://moonn.ru/lectures1",
        "https://moonn.ru/microbiom",
        "https://moonn.ru/novosti",
        "https://moonn.ru/otzivi",
        "https://moonn.ru/panicheskie_ataki",
        "https://moonn.ru/phytotherapy",
        "https://moonn.ru/platnye-treningi-seminary-programmy-tatiana-moonn",
        "https://moonn.ru/programmakursa",
        "https://moonn.ru/psiholog",
        "https://moonn.ru/psiholog-konsultacii-moskva",
        "https://moonn.ru/psiholog_moskva",
        "https://moonn.ru/psihology",
        "https://moonn.ru/psy4psy",
        "https://moonn.ru/psychoanalys",
        "https://moonn.ru/psypodgotovka1",
        "https://moonn.ru/recomend",
        "https://moonn.ru/salt",
        "https://moonn.ru/schematherapy",
        "https://moonn.ru/selfharm",
        "https://moonn.ru/semeynie_konflikti_article",
        "https://moonn.ru/semeyniy_psiholog",
        "https://moonn.ru/seminar555",
        "https://moonn.ru/shppp333",
        "https://moonn.ru/speaker",
        "https://moonn.ru/trauma",
        "https://moonn.ru/uslugi_aerofobia",
        "https://moonn.ru/uslugi_depression",
        "https://moonn.ru/uslugi_fin_blocks",
        "https://moonn.ru/uslugi_gtr",
        "https://moonn.ru/uslugi_konflikti_na_rabote",
        "https://moonn.ru/uslugi_lubovnaya_zavisimost",
        "https://moonn.ru/uslugi_obida_na_roditelei",
        "https://moonn.ru/uslugi_otnosheniya_v_kollektive",
        "https://moonn.ru/uslugi_podrostki",
        "https://moonn.ru/uslugi_procrastination",
        "https://moonn.ru/uslugi_razvod",
        "https://moonn.ru/uslugi_sohranit_brak",
        "https://moonn.ru/vacuum_cups",
        "https://moonn.ru/vigoranie_article",
        "https://moonn.ru/vospitanie_article",
        "https://moonn.ru/vystupleniya-lekcii-treningi-psiholog-tatiana-moonn",
        "https://moonn.ru/water"
      ],
      "review_noindex_or_rename_slug": [
        "https://moonn.ru/st1",
        "https://moonn.ru/st2"
      ]
    },
    "durationSeconds": 41.78
  },
  "pages": [
    {
      "url": "https://moonn.ru/",
      "lastmod": "",
      "status": 200,
      "contentType": "text/html; charset=UTF-8",
      "kind": "home",
      "robotsTxtBlocked": false,
      "title": "Татьяна Мунн — психолог МГУ в Москве и онлайн",
      "titleLength": 45,
      "description": "Татьяна Мунн (Кумскова Татьяна Михайловна) — психолог МГУ: консультации в Москве и онлайн, эмоциональный интеллект, отношения, стресс и подростки.",
      "descriptionLength": 146,
      "canonical": "https://moonn.ru/",
      "robots": "",
      "ogImagePresent": true,
      "h1Count": 5,
      "h1": [
        "ТЕМЫ ЛЕКЦИЙ, КОТОРЫЕ Я ЧИТАЮ",
        "ТЕМЫ ЛЕКЦИЙ, КОТОРЫЕ ЧИТАЮ",
        "ОБРАЗОВАНИЕ - МГУ"
      ],
      "jsonLdCount": 0,
      "imageCount": 55,
      "imagesMissingAlt": 55,
      "issues": [
        "images_missing_alt",
        "missing_jsonld",
        "multiple_h1"
      ],
      "decision": "strengthen_seo"
    },
    {
      "url": "https://moonn.ru/abuse_gaslight",
      "lastmod": "",
      "status": 200,
      "contentType": "text/html; charset=UTF-8",
      "kind": "other",
      "robotsTxtBlocked": false,
      "title": "Абьюз и газлайтинг | психолог Татьяна Мунн",
      "titleLength": 42,
      "description": "Абьюз и газлайтинг: материал Татьяны Мунн, психолога МГУ, о практической психологии, эмоциях, отношениях и саморегуляции.",
      "descriptionLength": 121,
      "canonical": "https://moonn.ru/abuse_gaslight",
      "robots": "",
      "ogImagePresent": true,
      "h1Count": 1,
      "h1": [
        "Абьюзинг и газлайтинг"
      ],
      "jsonLdCount": 0,
      "imageCount": 11,
      "imagesMissingAlt": 11,
      "issues": [
        "images_missing_alt",
        "missing_jsonld"
      ],
      "decision": "strengthen_seo"
    },
    {
      "url": "https://moonn.ru/aromatherapy",
      "lastmod": "",
      "status": 200,
      "contentType": "text/html; charset=UTF-8",
      "kind": "other",
      "robotsTxtBlocked": false,
      "title": "Ароматерапия и эмоциональное состояние | психолог Татьяна Мунн",
      "titleLength": 62,
      "description": "Ароматерапия и эмоциональное состояние: материал Татьяны Мунн, психолога МГУ, о практической психологии, эмоциях, отношениях и саморегуляции.",
      "descriptionLength": 141,
      "canonical": "https://moonn.ru/aromatherapy",
      "robots": "",
      "ogImagePresent": true,
      "h1Count": 1,
      "h1": [
        "Ароматерапия и психология"
      ],
      "jsonLdCount": 0,
      "imageCount": 19,
      "imagesMissingAlt": 19,
      "issues": [
        "images_missing_alt",
        "missing_jsonld"
      ],
      "decision": "strengthen_seo"
    },
    {
      "url": "https://moonn.ru/article_diary_of_emotions",
      "lastmod": "",
      "status": 200,
      "contentType": "text/html; charset=UTF-8",
      "kind": "article",
      "robotsTxtBlocked": false,
      "title": "Дневник эмоций | Татьяна Мунн",
      "titleLength": 29,
      "description": "Дневник эмоций: авторская статья Татьяны Мунн, психолога МГУ, о поведении, эмоциях, отношениях и саморегуляции.",
      "descriptionLength": 111,
      "canonical": "https://moonn.ru/article_diary_of_emotions",
      "robots": "",
      "ogImagePresent": true,
      "h1Count": 1,
      "h1": [
        "Как вести дневник эмоций"
      ],
      "jsonLdCount": 0,
      "imageCount": 14,
      "imagesMissingAlt": 14,
      "issues": [
        "images_missing_alt",
        "missing_jsonld"
      ],
      "decision": "strengthen_seo"
    },
    {
      "url": "https://moonn.ru/article_femininity",
      "lastmod": "",
      "status": 200,
      "contentType": "text/html; charset=UTF-8",
      "kind": "article",
      "robotsTxtBlocked": false,
      "title": "Женственность в отношениях | Татьяна Мунн",
      "titleLength": 41,
      "description": "Женственность в отношениях: авторская статья Татьяны Мунн, психолога МГУ, о поведении, эмоциях, отношениях и саморегуляции.",
      "descriptionLength": 123,
      "canonical": "https://moonn.ru/article_femininity",
      "robots": "",
      "ogImagePresent": true,
      "h1Count": 1,
      "h1": [
        "Потеря женственности в отношениях"
      ],
      "jsonLdCount": 0,
      "imageCount": 8,
      "imagesMissingAlt": 8,
      "issues": [
        "images_missing_alt",
        "missing_jsonld"
      ],
      "decision": "strengthen_seo"
    },
    {
      "url": "https://moonn.ru/article_gadget_addiction",
      "lastmod": "",
      "status": 200,
      "contentType": "text/html; charset=UTF-8",
      "kind": "article",
      "robotsTxtBlocked": false,
      "title": "Зависимость подростков от гаджетов | Татьяна Мунн",
      "titleLength": 49,
      "description": "Зависимость подростков от гаджетов: авторская статья Татьяны Мунн, психолога МГУ, о поведении, эмоциях, отношениях и саморегуляции.",
      "descriptionLength": 131,
      "canonical": "https://moonn.ru/article_gadget_addiction",
      "robots": "",
      "ogImagePresent": true,
      "h1Count": 1,
      "h1": [
        "Зависимость подростков от гаджетов и социальных сетей"
      ],
      "jsonLdCount": 0,
      "imageCount": 19,
      "imagesMissingAlt": 19,
      "issues": [
        "images_missing_alt",
        "missing_jsonld"
      ],
      "decision": "strengthen_seo"
    },
    {
      "url": "https://moonn.ru/article_toxic_job",
      "lastmod": "",
      "status": 200,
      "contentType": "text/html; charset=UTF-8",
      "kind": "article",
      "robotsTxtBlocked": false,
      "title": "Негативные эмоции на работе | Татьяна Мунн",
      "titleLength": 42,
      "description": "Негативные эмоции на работе: авторская статья Татьяны Мунн, психолога МГУ, о поведении, эмоциях, отношениях и саморегуляции.",
      "descriptionLength": 124,
      "canonical": "https://moonn.ru/article_toxic_job",
      "robots": "",
      "ogImagePresent": true,
      "h1Count": 1,
      "h1": [
        "как справиться с негативными эмоциями других людей"
      ],
      "jsonLdCount": 0,
      "imageCount": 2,
      "imagesMissingAlt": 2,
      "issues": [
        "images_missing_alt",
        "missing_jsonld"
      ],
      "decision": "strengthen_seo"
    },
    {
      "url": "https://moonn.ru/articles/eq-dlya-rukovoditeley",
      "lastmod": "",
      "status": 200,
      "contentType": "text/html; charset=UTF-8",
      "kind": "article",
      "robotsTxtBlocked": false,
      "title": "Эмоциональный интеллект руководителя | Татьяна Мунн",
      "titleLength": 51,
      "description": "Эмоциональный интеллект руководителя: авторская статья Татьяны Мунн, психолога МГУ, о поведении, эмоциях, отношениях и саморегуляции.",
      "descriptionLength": 133,
      "canonical": "https://moonn.ru/articles/eq-dlya-rukovoditeley",
      "robots": "",
      "ogImagePresent": true,
      "h1Count": 1,
      "h1": [
        "Эмоциональный интеллект лидера"
      ],
      "jsonLdCount": 0,
      "imageCount": 2,
      "imagesMissingAlt": 2,
      "issues": [
        "images_missing_alt",
        "missing_jsonld"
      ],
      "decision": "strengthen_seo"
    },
    {
      "url": "https://moonn.ru/baza-znaniy-emocionalnyy-intellekt-psihologiya",
      "lastmod": "",
      "status": 200,
      "contentType": "text/html; charset=UTF-8",
      "kind": "other",
      "robotsTxtBlocked": false,
      "title": "База знаний по психологии и эмоциональному интеллекту | психолог",
      "titleLength": 64,
      "description": "База знаний по психологии и эмоциональному интеллекту: материал Татьяны Мунн, психолога МГУ, о практической психологии, эмоциях, отношениях и саморегуляции.",
      "descriptionLength": 156,
      "canonical": "https://moonn.ru/baza-znaniy-emocionalnyy-intellekt-psihologiya",
      "robots": "",
      "ogImagePresent": true,
      "h1Count": 1,
      "h1": [
        "Полезная информация по ПСИХОЛОГИИ"
      ],
      "jsonLdCount": 0,
      "imageCount": 5,
      "imagesMissingAlt": 5,
      "issues": [
        "images_missing_alt",
        "missing_jsonld"
      ],
      "decision": "strengthen_seo"
    },
    {
      "url": "https://moonn.ru/eintellect",
      "lastmod": "",
      "status": 200,
      "contentType": "text/html; charset=UTF-8",
      "kind": "other",
      "robotsTxtBlocked": false,
      "title": "Эмоциональный интеллект | психолог Татьяна Мунн",
      "titleLength": 47,
      "description": "Эмоциональный интеллект: материал Татьяны Мунн, психолога МГУ, о практической психологии, эмоциях, отношениях и саморегуляции.",
      "descriptionLength": 126,
      "canonical": "https://moonn.ru/eintellect",
      "robots": "",
      "ogImagePresent": true,
      "h1Count": 1,
      "h1": [
        "Эмоциональный интеллект"
      ],
      "jsonLdCount": 0,
      "imageCount": 5,
      "imagesMissingAlt": 5,
      "issues": [
        "duplicate_description",
        "duplicate_title",
        "images_missing_alt",
        "missing_jsonld"
      ],
      "decision": "strengthen_seo"
    },
    {
      "url": "https://moonn.ru/emotional-intelligence/",
      "lastmod": "",
      "status": 200,
      "contentType": "text/html; charset=UTF-8",
      "kind": "other",
      "robotsTxtBlocked": false,
      "title": "Эмоциональный интеллект | психолог Татьяна Мунн",
      "titleLength": 47,
      "description": "Эмоциональный интеллект: материал Татьяны Мунн, психолога МГУ, о практической психологии, эмоциях, отношениях и саморегуляции.",
      "descriptionLength": 126,
      "canonical": "https://moonn.ru/emotional-intelligence/",
      "robots": "",
      "ogImagePresent": true,
      "h1Count": 0,
      "h1": [],
      "jsonLdCount": 0,
      "imageCount": 4,
      "imagesMissingAlt": 4,
      "issues": [
        "duplicate_description",
        "duplicate_title",
        "images_missing_alt",
        "missing_h1",
        "missing_jsonld"
      ],
      "decision": "strengthen_seo"
    },
    {
      "url": "https://moonn.ru/emotional-intelligence/articles",
      "lastmod": "",
      "status": 200,
      "contentType": "text/html; charset=UTF-8",
      "kind": "article",
      "robotsTxtBlocked": false,
      "title": "Статьи по эмоциональному интеллекту | Татьяна Мунн",
      "titleLength": 50,
      "description": "Статьи по эмоциональному интеллекту: авторская статья Татьяны Мунн, психолога МГУ, о поведении, эмоциях, отношениях и саморегуляции.",
      "descriptionLength": 132,
      "canonical": "https://moonn.ru/emotional-intelligence/articles",
      "robots": "",
      "ogImagePresent": true,
      "h1Count": 0,
      "h1": [],
      "jsonLdCount": 0,
      "imageCount": 2,
      "imagesMissingAlt": 2,
      "issues": [
        "images_missing_alt",
        "missing_h1",
        "missing_jsonld"
      ],
      "decision": "strengthen_seo"
    },
    {
      "url": "https://moonn.ru/emotional-intelligence/articles/benefits-of-ei",
      "lastmod": "",
      "status": 200,
      "contentType": "text/html; charset=UTF-8",
      "kind": "article",
      "robotsTxtBlocked": false,
      "title": "Преимущества эмоционального интеллекта: что даёт развитый EQ в",
      "titleLength": 62,
      "description": "Преимущества эмоционального интеллекта: что даёт развитый EQ в жизни и: авторская статья Татьяны Мунн, психолога МГУ, о поведении, эмоциях, отношениях и.",
      "descriptionLength": 153,
      "canonical": "https://moonn.ru/emotional-intelligence/articles/benefits-of-ei",
      "robots": "",
      "ogImagePresent": true,
      "h1Count": 0,
      "h1": [],
      "jsonLdCount": 0,
      "imageCount": 2,
      "imagesMissingAlt": 2,
      "issues": [
        "images_missing_alt",
        "missing_h1",
        "missing_jsonld"
      ],
      "decision": "strengthen_seo"
    },
    {
      "url": "https://moonn.ru/emotional-intelligence/articles/emotional-intelligence-skills",
      "lastmod": "",
      "status": 200,
      "contentType": "text/html; charset=UTF-8",
      "kind": "article",
      "robotsTxtBlocked": false,
      "title": "5 ключевых навыков эмоционального интеллекта: от осознанности до",
      "titleLength": 64,
      "description": "5 ключевых навыков эмоционального интеллекта: от осознанности до влияния: авторская статья Татьяны Мунн, психолога МГУ, о поведении, эмоциях, отношениях и.",
      "descriptionLength": 155,
      "canonical": "https://moonn.ru/emotional-intelligence/articles/emotional-intelligence-skills",
      "robots": "",
      "ogImagePresent": true,
      "h1Count": 0,
      "h1": [],
      "jsonLdCount": 0,
      "imageCount": 2,
      "imagesMissingAlt": 2,
      "issues": [
        "images_missing_alt",
        "missing_h1",
        "missing_jsonld"
      ],
      "decision": "strengthen_seo"
    },
    {
      "url": "https://moonn.ru/emotional-intelligence/articles/what-is-emotional-intelligence",
      "lastmod": "",
      "status": 200,
      "contentType": "text/html; charset=UTF-8",
      "kind": "article",
      "robotsTxtBlocked": false,
      "title": "Что такое эмоциональный интеллект? | Татьяна Мунн",
      "titleLength": 49,
      "description": "Что такое эмоциональный интеллект?: авторская статья Татьяны Мунн, психолога МГУ, о поведении, эмоциях, отношениях и саморегуляции.",
      "descriptionLength": 131,
      "canonical": "https://moonn.ru/emotional-intelligence/articles/what-is-emotional-intelligence",
      "robots": "",
      "ogImagePresent": true,
      "h1Count": 0,
      "h1": [],
      "jsonLdCount": 0,
      "imageCount": 3,
      "imagesMissingAlt": 2,
      "issues": [
        "images_missing_alt",
        "missing_h1",
        "missing_jsonld"
      ],
      "decision": "strengthen_seo"
    },
    {
      "url": "https://moonn.ru/emotional-intelligence/articles/why-ei-matters",
      "lastmod": "",
      "status": 200,
      "contentType": "text/html; charset=UTF-8",
      "kind": "article",
      "robotsTxtBlocked": false,
      "title": "Почему эмоциональный интеллект важнее IQ в карьере и жизни |",
      "titleLength": 60,
      "description": "Почему эмоциональный интеллект важнее IQ в карьере и жизни | Научные: авторская статья Татьяны Мунн, психолога МГУ, о поведении, эмоциях, отношениях и.",
      "descriptionLength": 151,
      "canonical": "https://moonn.ru/emotional-intelligence/articles/why-ei-matters",
      "robots": "",
      "ogImagePresent": true,
      "h1Count": 0,
      "h1": [],
      "jsonLdCount": 0,
      "imageCount": 2,
      "imagesMissingAlt": 2,
      "issues": [
        "images_missing_alt",
        "missing_h1",
        "missing_jsonld"
      ],
      "decision": "strengthen_seo"
    },
    {
      "url": "https://moonn.ru/emotional-intelligence/diagnostoka-ei",
      "lastmod": "",
      "status": 200,
      "contentType": "text/html; charset=UTF-8",
      "kind": "other",
      "robotsTxtBlocked": false,
      "title": "Диагностика эмоционального интеллекта: как измерить свой EQ | Тесты",
      "titleLength": 67,
      "description": "Диагностика эмоционального интеллекта: как измерить свой EQ | Тесты и: материал Татьяны Мунн, психолога МГУ, о практической психологии, эмоциях, отношениях и.",
      "descriptionLength": 158,
      "canonical": "https://moonn.ru/emotional-intelligence/diagnostoka-ei",
      "robots": "",
      "ogImagePresent": true,
      "h1Count": 0,
      "h1": [],
      "jsonLdCount": 0,
      "imageCount": 3,
      "imagesMissingAlt": 3,
      "issues": [
        "images_missing_alt",
        "missing_h1",
        "missing_jsonld"
      ],
      "decision": "strengthen_seo"
    },
    {
      "url": "https://moonn.ru/emotional-intelligence/ei-leader-12",
      "lastmod": "",
      "status": 200,
      "contentType": "text/html; charset=UTF-8",
      "kind": "other",
      "robotsTxtBlocked": false,
      "title": "Эмоциональный интеллект лидера | психолог Татьяна Мунн",
      "titleLength": 54,
      "description": "Эмоциональный интеллект лидера: материал Татьяны Мунн, психолога МГУ, о практической психологии, эмоциях, отношениях и саморегуляции.",
      "descriptionLength": 133,
      "canonical": "https://moonn.ru/emotional-intelligence/ei-leader-12",
      "robots": "",
      "ogImagePresent": true,
      "h1Count": 0,
      "h1": [],
      "jsonLdCount": 0,
      "imageCount": 2,
      "imagesMissingAlt": 2,
      "issues": [
        "images_missing_alt",
        "missing_h1",
        "missing_jsonld"
      ],
      "decision": "strengthen_seo"
    },
    {
      "url": "https://moonn.ru/emotional-intelligence/knowledge-base",
      "lastmod": "",
      "status": 200,
      "contentType": "text/html; charset=UTF-8",
      "kind": "knowledge_base",
      "robotsTxtBlocked": false,
      "title": "База знаний по эмоциональному интеллекту | Татьяна Мунн",
      "titleLength": 55,
      "description": "База знаний по эмоциональному интеллекту: справочный материал Татьяны Мунн по эмоциональному интеллекту, коммуникации, саморегуляции и устойчивости.",
      "descriptionLength": 148,
      "canonical": "https://moonn.ru/emotional-intelligence/knowledge-base",
      "robots": "",
      "ogImagePresent": true,
      "h1Count": 0,
      "h1": [],
      "jsonLdCount": 0,
      "imageCount": 2,
      "imagesMissingAlt": 2,
      "issues": [
        "images_missing_alt",
        "missing_h1",
        "missing_jsonld"
      ],
      "decision": "strengthen_seo"
    },
    {
      "url": "https://moonn.ru/emotional-intelligence/knowledge-base/active-listening",
      "lastmod": "",
      "status": 200,
      "contentType": "text/html; charset=UTF-8",
      "kind": "knowledge_base",
      "robotsTxtBlocked": false,
      "title": "Активное слушание: как научиться слышать и понимать людей | Татьяна",
      "titleLength": 67,
      "description": "Активное слушание: как научиться слышать и понимать людей: справочный материал Татьяны Мунн по эмоциональному интеллекту, коммуникации, саморегуляции и.",
      "descriptionLength": 152,
      "canonical": "https://moonn.ru/emotional-intelligence/knowledge-base/active-listening",
      "robots": "",
      "ogImagePresent": true,
      "h1Count": 0,
      "h1": [],
      "jsonLdCount": 0,
      "imageCount": 8,
      "imagesMissingAlt": 7,
      "issues": [
        "images_missing_alt",
        "missing_h1",
        "missing_jsonld"
      ],
      "decision": "strengthen_seo"
    },
    {
      "url": "https://moonn.ru/emotional-intelligence/knowledge-base/burnout",
      "lastmod": "",
      "status": 200,
      "contentType": "text/html; charset=UTF-8",
      "kind": "knowledge_base",
      "robotsTxtBlocked": false,
      "title": "Выгорание: признаки, причины и восстановление | Татьяна Мунн",
      "titleLength": 60,
      "description": "Выгорание: признаки, причины и восстановление: справочный материал Татьяны Мунн по эмоциональному интеллекту, коммуникации, саморегуляции и устойчивости.",
      "descriptionLength": 153,
      "canonical": "https://moonn.ru/emotional-intelligence/knowledge-base/burnout",
      "robots": "",
      "ogImagePresent": true,
      "h1Count": 0,
      "h1": [],
      "jsonLdCount": 0,
      "imageCount": 8,
      "imagesMissingAlt": 7,
      "issues": [
        "images_missing_alt",
        "missing_h1",
        "missing_jsonld"
      ],
      "decision": "strengthen_seo"
    },
    {
      "url": "https://moonn.ru/emotional-intelligence/knowledge-base/emotional-contagion",
      "lastmod": "",
      "status": 200,
      "contentType": "text/html; charset=UTF-8",
      "kind": "knowledge_base",
      "robotsTxtBlocked": false,
      "title": "Эмоциональное заражение: как эмоции передаются людям и командам |",
      "titleLength": 65,
      "description": "Эмоциональное заражение: как эмоции передаются людям и командам: справочный материал Татьяны Мунн по эмоциональному интеллекту, коммуникации, саморегуляции и.",
      "descriptionLength": 158,
      "canonical": "https://moonn.ru/emotional-intelligence/knowledge-base/emotional-contagion",
      "robots": "",
      "ogImagePresent": true,
      "h1Count": 0,
      "h1": [],
      "jsonLdCount": 0,
      "imageCount": 8,
      "imagesMissingAlt": 7,
      "issues": [
        "images_missing_alt",
        "missing_h1",
        "missing_jsonld"
      ],
      "decision": "strengthen_seo"
    },
    {
      "url": "https://moonn.ru/emotional-intelligence/knowledge-base/emotional-intelligence",
      "lastmod": "",
      "status": 200,
      "contentType": "text/html; charset=UTF-8",
      "kind": "knowledge_base",
      "robotsTxtBlocked": false,
      "title": "Что такое эмоциональный интеллект и как он работает | Татьяна Мунн",
      "titleLength": 66,
      "description": "Что такое эмоциональный интеллект и как он работает: справочный материал Татьяны Мунн по эмоциональному интеллекту, коммуникации, саморегуляции и.",
      "descriptionLength": 146,
      "canonical": "https://moonn.ru/emotional-intelligence/knowledge-base/emotional-intelligence",
      "robots": "",
      "ogImagePresent": true,
      "h1Count": 0,
      "h1": [],
      "jsonLdCount": 0,
      "imageCount": 7,
      "imagesMissingAlt": 6,
      "issues": [
        "images_missing_alt",
        "missing_h1",
        "missing_jsonld"
      ],
      "decision": "strengthen_seo"
    },
    {
      "url": "https://moonn.ru/emotional-intelligence/knowledge-base/emotional-literacy",
      "lastmod": "",
      "status": 200,
      "contentType": "text/html; charset=UTF-8",
      "kind": "knowledge_base",
      "robotsTxtBlocked": false,
      "title": "Эмоциональная грамотность — навык точного выражения чувств |",
      "titleLength": 60,
      "description": "Эмоциональная грамотность — навык точного выражения чувств: справочный материал Татьяны Мунн по эмоциональному интеллекту, коммуникации, саморегуляции и.",
      "descriptionLength": 153,
      "canonical": "https://moonn.ru/emotional-intelligence/knowledge-base/emotional-literacy",
      "robots": "",
      "ogImagePresent": true,
      "h1Count": 0,
      "h1": [],
      "jsonLdCount": 0,
      "imageCount": 7,
      "imagesMissingAlt": 6,
      "issues": [
        "images_missing_alt",
        "missing_h1",
        "missing_jsonld"
      ],
      "decision": "strengthen_seo"
    },
    {
      "url": "https://moonn.ru/emotional-intelligence/knowledge-base/emotional-maturity",
      "lastmod": "",
      "status": 200,
      "contentType": "text/html; charset=UTF-8",
      "kind": "knowledge_base",
      "robotsTxtBlocked": false,
      "title": "Эмоциональная зрелость: как отличить и развивать | Татьяна Мунн",
      "titleLength": 63,
      "description": "Эмоциональная зрелость: как отличить и развивать: справочный материал Татьяны Мунн по эмоциональному интеллекту, коммуникации, саморегуляции и устойчивости.",
      "descriptionLength": 156,
      "canonical": "https://moonn.ru/emotional-intelligence/knowledge-base/emotional-maturity",
      "robots": "",
      "ogImagePresent": true,
      "h1Count": 0,
      "h1": [],
      "jsonLdCount": 0,
      "imageCount": 7,
      "imagesMissingAlt": 7,
      "issues": [
        "images_missing_alt",
        "missing_h1",
        "missing_jsonld"
      ],
      "decision": "strengthen_seo"
    },
    {
      "url": "https://moonn.ru/emotional-intelligence/knowledge-base/empathy",
      "lastmod": "",
      "status": 200,
      "contentType": "text/html; charset=UTF-8",
      "kind": "knowledge_base",
      "robotsTxtBlocked": false,
      "title": "Эмпатия — ключевой навык эмоционального интеллекта | Татьяна Мунн",
      "titleLength": 65,
      "description": "Эмпатия — ключевой навык эмоционального интеллекта: справочный материал Татьяны Мунн по эмоциональному интеллекту, коммуникации, саморегуляции и устойчивости.",
      "descriptionLength": 158,
      "canonical": "https://moonn.ru/emotional-intelligence/knowledge-base/empathy",
      "robots": "",
      "ogImagePresent": true,
      "h1Count": 0,
      "h1": [],
      "jsonLdCount": 0,
      "imageCount": 8,
      "imagesMissingAlt": 7,
      "issues": [
        "images_missing_alt",
        "missing_h1",
        "missing_jsonld"
      ],
      "decision": "strengthen_seo"
    },
    {
      "url": "https://moonn.ru/emotional-intelligence/knowledge-base/intrinsic-motivation",
      "lastmod": "",
      "status": 200,
      "contentType": "text/html; charset=UTF-8",
      "kind": "knowledge_base",
      "robotsTxtBlocked": false,
      "title": "Внутренняя мотивация: как её развивать и не потерять | психолог и",
      "titleLength": 65,
      "description": "Внутренняя мотивация: как её развивать и не потерять | психолог и: справочный материал Татьяны Мунн по эмоциональному интеллекту, коммуникации, саморегуляции.",
      "descriptionLength": 158,
      "canonical": "https://moonn.ru/emotional-intelligence/knowledge-base/intrinsic-motivation",
      "robots": "",
      "ogImagePresent": true,
      "h1Count": 0,
      "h1": [],
      "jsonLdCount": 0,
      "imageCount": 8,
      "imagesMissingAlt": 7,
      "issues": [
        "images_missing_alt",
        "missing_h1",
        "missing_jsonld"
      ],
      "decision": "strengthen_seo"
    },
    {
      "url": "https://moonn.ru/emotional-intelligence/knowledge-base/male-loneliness-russia",
      "lastmod": "",
      "status": 200,
      "contentType": "text/html; charset=UTF-8",
      "kind": "knowledge_base",
      "robotsTxtBlocked": false,
      "title": "Мужское одиночество в России: скрытый кризис, о котором не принято",
      "titleLength": 66,
      "description": "Мужское одиночество в России: скрытый кризис, о котором не принято: справочный материал Татьяны Мунн по эмоциональному интеллекту, коммуникации.",
      "descriptionLength": 144,
      "canonical": "https://moonn.ru/emotional-intelligence/knowledge-base/male-loneliness-russia",
      "robots": "",
      "ogImagePresent": true,
      "h1Count": 1,
      "h1": [
        "Мужское одиночество в России"
      ],
      "jsonLdCount": 0,
      "imageCount": 2,
      "imagesMissingAlt": 2,
      "issues": [
        "images_missing_alt",
        "missing_jsonld"
      ],
      "decision": "strengthen_seo"
    },
    {
      "url": "https://moonn.ru/emotional-intelligence/knowledge-base/nonviolent-communication",
      "lastmod": "",
      "status": 200,
      "contentType": "text/html; charset=UTF-8",
      "kind": "knowledge_base",
      "robotsTxtBlocked": false,
      "title": "Ненасильственное общение (ННО/NVC): как говорить без конфликта |",
      "titleLength": 64,
      "description": "Ненасильственное общение (ННО/NVC): как говорить без конфликта: справочный материал Татьяны Мунн по эмоциональному интеллекту, коммуникации, саморегуляции и.",
      "descriptionLength": 157,
      "canonical": "https://moonn.ru/emotional-intelligence/knowledge-base/nonviolent-communication",
      "robots": "",
      "ogImagePresent": true,
      "h1Count": 0,
      "h1": [],
      "jsonLdCount": 0,
      "imageCount": 8,
      "imagesMissingAlt": 7,
      "issues": [
        "images_missing_alt",
        "missing_h1",
        "missing_jsonld"
      ],
      "decision": "strengthen_seo"
    },
    {
      "url": "https://moonn.ru/emotional-intelligence/knowledge-base/personal-boundaries",
      "lastmod": "",
      "status": 200,
      "contentType": "text/html; charset=UTF-8",
      "kind": "knowledge_base",
      "robotsTxtBlocked": false,
      "title": "Личные границы: как их выстраивать и защищать | Татьяна Мунн",
      "titleLength": 60,
      "description": "Личные границы: как их выстраивать и защищать: справочный материал Татьяны Мунн по эмоциональному интеллекту, коммуникации, саморегуляции и устойчивости.",
      "descriptionLength": 153,
      "canonical": "https://moonn.ru/emotional-intelligence/knowledge-base/personal-boundaries",
      "robots": "",
      "ogImagePresent": true,
      "h1Count": 0,
      "h1": [],
      "jsonLdCount": 0,
      "imageCount": 8,
      "imagesMissingAlt": 7,
      "issues": [
        "images_missing_alt",
        "missing_h1",
        "missing_jsonld"
      ],
      "decision": "strengthen_seo"
    },
    {
      "url": "https://moonn.ru/emotional-intelligence/knowledge-base/psychological-safety",
      "lastmod": "",
      "status": 200,
      "contentType": "text/html; charset=UTF-8",
      "kind": "knowledge_base",
      "robotsTxtBlocked": false,
      "title": "Психологическая безопасность команды: что это и как её создать |",
      "titleLength": 64,
      "description": "Психологическая безопасность команды: что это и как её создать: справочный материал Татьяны Мунн по эмоциональному интеллекту, коммуникации, саморегуляции и.",
      "descriptionLength": 157,
      "canonical": "https://moonn.ru/emotional-intelligence/knowledge-base/psychological-safety",
      "robots": "",
      "ogImagePresent": true,
      "h1Count": 0,
      "h1": [],
      "jsonLdCount": 0,
      "imageCount": 8,
      "imagesMissingAlt": 7,
      "issues": [
        "images_missing_alt",
        "missing_h1",
        "missing_jsonld"
      ],
      "decision": "strengthen_seo"
    },
    {
      "url": "https://moonn.ru/emotional-intelligence/knowledge-base/self-awareness",
      "lastmod": "",
      "status": 200,
      "contentType": "text/html; charset=UTF-8",
      "kind": "knowledge_base",
      "robotsTxtBlocked": false,
      "title": "Самоосознанность: ключевой навык эмоционального интеллекта |",
      "titleLength": 60,
      "description": "Самоосознанность: ключевой навык эмоционального интеллекта: справочный материал Татьяны Мунн по эмоциональному интеллекту, коммуникации, саморегуляции и.",
      "descriptionLength": 153,
      "canonical": "https://moonn.ru/emotional-intelligence/knowledge-base/self-awareness",
      "robots": "",
      "ogImagePresent": true,
      "h1Count": 0,
      "h1": [],
      "jsonLdCount": 0,
      "imageCount": 7,
      "imagesMissingAlt": 6,
      "issues": [
        "images_missing_alt",
        "missing_h1",
        "missing_jsonld"
      ],
      "decision": "strengthen_seo"
    },
    {
      "url": "https://moonn.ru/emotional-intelligence/knowledge-base/self-regulation",
      "lastmod": "",
      "status": 200,
      "contentType": "text/html; charset=UTF-8",
      "kind": "knowledge_base",
      "robotsTxtBlocked": false,
      "title": "Саморегуляция — ключевой навык эмоционального интеллекта | Татьяна",
      "titleLength": 66,
      "description": "Саморегуляция — ключевой навык эмоционального интеллекта: справочный материал Татьяны Мунн по эмоциональному интеллекту, коммуникации, саморегуляции и.",
      "descriptionLength": 151,
      "canonical": "https://moonn.ru/emotional-intelligence/knowledge-base/self-regulation",
      "robots": "",
      "ogImagePresent": true,
      "h1Count": 0,
      "h1": [],
      "jsonLdCount": 0,
      "imageCount": 7,
      "imagesMissingAlt": 6,
      "issues": [
        "images_missing_alt",
        "missing_h1",
        "missing_jsonld"
      ],
      "decision": "strengthen_seo"
    },
    {
      "url": "https://moonn.ru/emotional-intelligence/knowledge-base/social-intelligence",
      "lastmod": "",
      "status": 200,
      "contentType": "text/html; charset=UTF-8",
      "kind": "knowledge_base",
      "robotsTxtBlocked": false,
      "title": "Социальные навыки и социальный интеллект: как развивать | Татьяна",
      "titleLength": 65,
      "description": "Социальные навыки и социальный интеллект: как развивать: справочный материал Татьяны Мунн по эмоциональному интеллекту, коммуникации, саморегуляции и.",
      "descriptionLength": 150,
      "canonical": "https://moonn.ru/emotional-intelligence/knowledge-base/social-intelligence",
      "robots": "",
      "ogImagePresent": true,
      "h1Count": 0,
      "h1": [],
      "jsonLdCount": 0,
      "imageCount": 7,
      "imagesMissingAlt": 6,
      "issues": [
        "images_missing_alt",
        "missing_h1",
        "missing_jsonld"
      ],
      "decision": "strengthen_seo"
    },
    {
      "url": "https://moonn.ru/events",
      "lastmod": "",
      "status": 200,
      "contentType": "text/html; charset=UTF-8",
      "kind": "lecture_or_events",
      "robotsTxtBlocked": false,
      "title": "Мероприятия Татьяны Мунн — психология и эмоциональный интеллект",
      "titleLength": 63,
      "description": "Мероприятия Татьяны Мунн: лекции и практические материалы Татьяны Мунн по психологии, эмоциональному интеллекту, отношениям и soft skills.",
      "descriptionLength": 138,
      "canonical": "https://moonn.ru/events",
      "robots": "",
      "ogImagePresent": true,
      "h1Count": 0,
      "h1": [],
      "jsonLdCount": 0,
      "imageCount": 2,
      "imagesMissingAlt": 2,
      "issues": [
        "images_missing_alt",
        "missing_h1",
        "missing_jsonld"
      ],
      "decision": "strengthen_seo"
    },
    {
      "url": "https://moonn.ru/events_tp",
      "lastmod": "",
      "status": 200,
      "contentType": "text/html; charset=UTF-8",
      "kind": "lecture_or_events",
      "robotsTxtBlocked": false,
      "title": "Лекции Татьяны Мунн по психологии — психология и эмоциональный",
      "titleLength": 62,
      "description": "Лекции Татьяны Мунн по психологии: лекции и практические материалы Татьяны Мунн по психологии, эмоциональному интеллекту, отношениям и soft skills.",
      "descriptionLength": 147,
      "canonical": "https://moonn.ru/events_tp",
      "robots": "",
      "ogImagePresent": true,
      "h1Count": 0,
      "h1": [],
      "jsonLdCount": 0,
      "imageCount": 2,
      "imagesMissingAlt": 2,
      "issues": [
        "images_missing_alt",
        "missing_h1",
        "missing_jsonld"
      ],
      "decision": "strengthen_seo"
    },
    {
      "url": "https://moonn.ru/geshtalt",
      "lastmod": "",
      "status": 200,
      "contentType": "text/html; charset=UTF-8",
      "kind": "other",
      "robotsTxtBlocked": false,
      "title": "Гештальт-подход | психолог Татьяна Мунн",
      "titleLength": 39,
      "description": "Гештальт-подход: материал Татьяны Мунн, психолога МГУ, о практической психологии, эмоциях, отношениях и саморегуляции.",
      "descriptionLength": 118,
      "canonical": "https://moonn.ru/geshtalt",
      "robots": "",
      "ogImagePresent": true,
      "h1Count": 1,
      "h1": [
        "Гештальт-терапия:"
      ],
      "jsonLdCount": 0,
      "imageCount": 4,
      "imagesMissingAlt": 4,
      "issues": [
        "images_missing_alt",
        "missing_jsonld"
      ],
      "decision": "strengthen_seo"
    },
    {
      "url": "https://moonn.ru/kpt",
      "lastmod": "",
      "status": 200,
      "contentType": "text/html; charset=UTF-8",
      "kind": "other",
      "robotsTxtBlocked": false,
      "title": "Когнитивно-поведенческая терапия | психолог Татьяна Мунн",
      "titleLength": 56,
      "description": "Когнитивно-поведенческая терапия: материал Татьяны Мунн, психолога МГУ, о практической психологии, эмоциях, отношениях и саморегуляции.",
      "descriptionLength": 135,
      "canonical": "https://moonn.ru/kpt",
      "robots": "",
      "ogImagePresent": true,
      "h1Count": 1,
      "h1": [
        "Когнитивно-поведенческая терапия (КПТ)"
      ],
      "jsonLdCount": 0,
      "imageCount": 4,
      "imagesMissingAlt": 4,
      "issues": [
        "images_missing_alt",
        "missing_jsonld"
      ],
      "decision": "strengthen_seo"
    },
    {
      "url": "https://moonn.ru/kurs-ei",
      "lastmod": "",
      "status": 200,
      "contentType": "text/html; charset=UTF-8",
      "kind": "other",
      "robotsTxtBlocked": false,
      "title": "Курс по эмоциональному интеллекту | психолог Татьяна Мунн",
      "titleLength": 57,
      "description": "Курс по эмоциональному интеллекту: материал Татьяны Мунн, психолога МГУ, о практической психологии, эмоциях, отношениях и саморегуляции.",
      "descriptionLength": 136,
      "canonical": "https://moonn.ru/kurs-ei",
      "robots": "",
      "ogImagePresent": true,
      "h1Count": 1,
      "h1": [
        "Курс про эмоциональный интеллект без скучной подачи"
      ],
      "jsonLdCount": 1,
      "imageCount": 9,
      "imagesMissingAlt": 2,
      "issues": [
        "images_missing_alt"
      ],
      "decision": "strengthen_seo"
    },
    {
      "url": "https://moonn.ru/lectures1",
      "lastmod": "",
      "status": 200,
      "contentType": "text/html; charset=UTF-8",
      "kind": "lecture_or_events",
      "robotsTxtBlocked": false,
      "title": "Архив лекций Татьяны Мунн — психология и эмоциональный интеллект",
      "titleLength": 64,
      "description": "Архив лекций Татьяны Мунн: лекции и практические материалы Татьяны Мунн по психологии, эмоциональному интеллекту, отношениям и soft skills.",
      "descriptionLength": 139,
      "canonical": "https://moonn.ru/lectures1",
      "robots": "",
      "ogImagePresent": true,
      "h1Count": 0,
      "h1": [],
      "jsonLdCount": 0,
      "imageCount": 6,
      "imagesMissingAlt": 6,
      "issues": [
        "images_missing_alt",
        "missing_h1",
        "missing_jsonld"
      ],
      "decision": "strengthen_seo"
    },
    {
      "url": "https://moonn.ru/microbiom",
      "lastmod": "",
      "status": 200,
      "contentType": "text/html; charset=UTF-8",
      "kind": "other",
      "robotsTxtBlocked": false,
      "title": "Микробиом и эмоциональное состояние | психолог Татьяна Мунн",
      "titleLength": 59,
      "description": "Микробиом и эмоциональное состояние: материал Татьяны Мунн, психолога МГУ, о практической психологии, эмоциях, отношениях и саморегуляции.",
      "descriptionLength": 138,
      "canonical": "https://moonn.ru/microbiom",
      "robots": "",
      "ogImagePresent": true,
      "h1Count": 0,
      "h1": [],
      "jsonLdCount": 0,
      "imageCount": 17,
      "imagesMissingAlt": 17,
      "issues": [
        "images_missing_alt",
        "missing_h1",
        "missing_jsonld"
      ],
      "decision": "strengthen_seo"
    },
    {
      "url": "https://moonn.ru/novosti",
      "lastmod": "",
      "status": 200,
      "contentType": "text/html; charset=UTF-8",
      "kind": "other",
      "robotsTxtBlocked": false,
      "title": "Командировка преподавателя МГУ Татьяны Мунн в филиал МГУ в г",
      "titleLength": 60,
      "description": "Командировка преподавателя МГУ Татьяны Мунн в филиал МГУ в г. Ташкенте: материал Татьяны Мунн, психолога МГУ, о практической психологии, эмоциях, отношениях.",
      "descriptionLength": 157,
      "canonical": "https://moonn.ru/novosti",
      "robots": "",
      "ogImagePresent": true,
      "h1Count": 0,
      "h1": [],
      "jsonLdCount": 0,
      "imageCount": 4,
      "imagesMissingAlt": 4,
      "issues": [
        "images_missing_alt",
        "missing_h1",
        "missing_jsonld"
      ],
      "decision": "strengthen_seo"
    },
    {
      "url": "https://moonn.ru/otzivi",
      "lastmod": "",
      "status": 200,
      "contentType": "text/html; charset=UTF-8",
      "kind": "other",
      "robotsTxtBlocked": false,
      "title": "Отзывы о психологе Татьяне Мунн | психолог Татьяна Мунн",
      "titleLength": 55,
      "description": "Отзывы о психологе Татьяне Мунн: материал Татьяны Мунн, психолога МГУ, о практической психологии, эмоциях, отношениях и саморегуляции.",
      "descriptionLength": 134,
      "canonical": "https://moonn.ru/otzivi",
      "robots": "",
      "ogImagePresent": true,
      "h1Count": 2,
      "h1": [
        "ОТЗЫВЫ КЛИЕНТОВ Психолог Татьяна Мунн",
        "Психолог Татьяна Мунн КОНТАКТЫ"
      ],
      "jsonLdCount": 0,
      "imageCount": 11,
      "imagesMissingAlt": 11,
      "issues": [
        "images_missing_alt",
        "missing_jsonld",
        "multiple_h1"
      ],
      "decision": "strengthen_seo"
    },
    {
      "url": "https://moonn.ru/panicheskie_ataki",
      "lastmod": "",
      "status": 200,
      "contentType": "text/html; charset=UTF-8",
      "kind": "other",
      "robotsTxtBlocked": false,
      "title": "Панические атаки | психолог Татьяна Мунн",
      "titleLength": 40,
      "description": "Панические атаки: материал Татьяны Мунн, психолога МГУ, о практической психологии, эмоциях, отношениях и саморегуляции.",
      "descriptionLength": 119,
      "canonical": "https://moonn.ru/panicheskie_ataki",
      "robots": "",
      "ogImagePresent": true,
      "h1Count": 7,
      "h1": [
        "Как БЫСТРО избавиться от ПАНИЧЕСКИХ АТАК?",
        "Симптомы Панические Атак",
        "Панические Атаки у ПОДРОСТКОВ"
      ],
      "jsonLdCount": 0,
      "imageCount": 14,
      "imagesMissingAlt": 14,
      "issues": [
        "images_missing_alt",
        "missing_jsonld",
        "multiple_h1"
      ],
      "decision": "strengthen_seo"
    },
    {
      "url": "https://moonn.ru/phytotherapy",
      "lastmod": "",
      "status": 200,
      "contentType": "text/html; charset=UTF-8",
      "kind": "other",
      "robotsTxtBlocked": false,
      "title": "Фитотерапия и эмоциональное состояние | психолог Татьяна Мунн",
      "titleLength": 61,
      "description": "Фитотерапия и эмоциональное состояние: материал Татьяны Мунн, психолога МГУ, о практической психологии, эмоциях, отношениях и саморегуляции.",
      "descriptionLength": 140,
      "canonical": "https://moonn.ru/phytotherapy",
      "robots": "",
      "ogImagePresent": true,
      "h1Count": 0,
      "h1": [],
      "jsonLdCount": 0,
      "imageCount": 9,
      "imagesMissingAlt": 9,
      "issues": [
        "images_missing_alt",
        "missing_h1",
        "missing_jsonld"
      ],
      "decision": "strengthen_seo"
    },
    {
      "url": "https://moonn.ru/platnye-treningi-seminary-programmy-tatiana-moonn",
      "lastmod": "",
      "status": 200,
      "contentType": "text/html; charset=UTF-8",
      "kind": "other",
      "robotsTxtBlocked": false,
      "title": "Платные тренинги и лекции Татьяны Мунн | психолог Татьяна Мунн",
      "titleLength": 62,
      "description": "Платные тренинги и лекции Татьяны Мунн: материал Татьяны Мунн, психолога МГУ, о практической психологии, эмоциях, отношениях и саморегуляции.",
      "descriptionLength": 141,
      "canonical": "https://moonn.ru/platnye-treningi-seminary-programmy-tatiana-moonn",
      "robots": "",
      "ogImagePresent": true,
      "h1Count": 0,
      "h1": [],
      "jsonLdCount": 0,
      "imageCount": 12,
      "imagesMissingAlt": 11,
      "issues": [
        "images_missing_alt",
        "missing_h1",
        "missing_jsonld"
      ],
      "decision": "strengthen_seo"
    },
    {
      "url": "https://moonn.ru/programmakursa",
      "lastmod": "",
      "status": 200,
      "contentType": "text/html; charset=UTF-8",
      "kind": "other",
      "robotsTxtBlocked": false,
      "title": "Программа курса по эмоциональному интеллекту | психолог Татьяна Мунн",
      "titleLength": 68,
      "description": "Программа курса по эмоциональному интеллекту: материал Татьяны Мунн, психолога МГУ, о практической психологии, эмоциях, отношениях и саморегуляции.",
      "descriptionLength": 147,
      "canonical": "https://moonn.ru/programmakursa",
      "robots": "",
      "ogImagePresent": true,
      "h1Count": 1,
      "h1": [
        "Программа курса по эмоциональному интеллекту"
      ],
      "jsonLdCount": 0,
      "imageCount": 5,
      "imagesMissingAlt": 2,
      "issues": [
        "images_missing_alt",
        "missing_jsonld"
      ],
      "decision": "strengthen_seo"
    },
    {
      "url": "https://moonn.ru/psiholog",
      "lastmod": "",
      "status": 200,
      "contentType": "text/html; charset=UTF-8",
      "kind": "other",
      "robotsTxtBlocked": false,
      "title": "Психолог в Москве и онлайн: Татьяна Мунн, психолог МГУ",
      "titleLength": 54,
      "description": "Психолог МГУ Татьяна Мунн: консультации в Москве и онлайн, эмоциональный интеллект, стресс, отношения и поддержка взрослых и подростков.",
      "descriptionLength": 136,
      "canonical": "https://moonn.ru/psiholog-konsultacii-moskva",
      "robots": "",
      "ogImagePresent": true,
      "h1Count": 0,
      "h1": [],
      "jsonLdCount": 0,
      "imageCount": 12,
      "imagesMissingAlt": 10,
      "issues": [
        "canonical_mismatch",
        "images_missing_alt",
        "missing_h1",
        "missing_jsonld"
      ],
      "decision": "strengthen_seo"
    },
    {
      "url": "https://moonn.ru/psiholog-konsultacii-moskva",
      "lastmod": "",
      "status": 200,
      "contentType": "text/html; charset=UTF-8",
      "kind": "service",
      "robotsTxtBlocked": false,
      "title": "Консультации психолога в Москве и онлайн: психолог МГУ Татьяна Мунн",
      "titleLength": 67,
      "description": "Консультации психолога в Москве и онлайн: консультации Татьяны Мунн, психолога МГУ, в Москве и онлайн. Стресс, отношения, эмоции и личные состояния.",
      "descriptionLength": 148,
      "canonical": "https://moonn.ru/psiholog-konsultacii-moskva",
      "robots": "",
      "ogImagePresent": true,
      "h1Count": 2,
      "h1": [
        "Психологические Консультации в Москве Психолог МГУ - Татьяна Мунн",
        "ОБРАЗОВАНИЕ - МГУ"
      ],
      "jsonLdCount": 0,
      "imageCount": 13,
      "imagesMissingAlt": 12,
      "issues": [
        "images_missing_alt",
        "missing_jsonld",
        "multiple_h1"
      ],
      "decision": "strengthen_seo"
    },
    {
      "url": "https://moonn.ru/psiholog_moskva",
      "lastmod": "",
      "status": 200,
      "contentType": "text/html; charset=UTF-8",
      "kind": "service",
      "robotsTxtBlocked": false,
      "title": "Психолог в Москве: психолог МГУ Татьяна Мунн",
      "titleLength": 44,
      "description": "Психолог в Москве: консультации Татьяны Мунн, психолога МГУ, в Москве и онлайн. Стресс, отношения, эмоции и личные состояния.",
      "descriptionLength": 125,
      "canonical": "https://moonn.ru/psiholog_moskva",
      "robots": "",
      "ogImagePresent": true,
      "h1Count": 0,
      "h1": [],
      "jsonLdCount": 0,
      "imageCount": 7,
      "imagesMissingAlt": 7,
      "issues": [
        "images_missing_alt",
        "missing_h1",
        "missing_jsonld"
      ],
      "decision": "strengthen_seo"
    },
    {
      "url": "https://moonn.ru/psihology",
      "lastmod": "",
      "status": 200,
      "contentType": "text/html; charset=UTF-8",
      "kind": "other",
      "robotsTxtBlocked": false,
      "title": "Психологическая помощь в Москве и онлайн | психолог Татьяна Мунн",
      "titleLength": 64,
      "description": "Психологическая помощь в Москве и онлайн: материал Татьяны Мунн, психолога МГУ, о практической психологии, эмоциях, отношениях и саморегуляции.",
      "descriptionLength": 143,
      "canonical": "https://moonn.ru/psihology",
      "robots": "",
      "ogImagePresent": true,
      "h1Count": 0,
      "h1": [],
      "jsonLdCount": 0,
      "imageCount": 9,
      "imagesMissingAlt": 9,
      "issues": [
        "images_missing_alt",
        "missing_h1",
        "missing_jsonld"
      ],
      "decision": "strengthen_seo"
    },
    {
      "url": "https://moonn.ru/psy4psy",
      "lastmod": "",
      "status": 200,
      "contentType": "text/html; charset=UTF-8",
      "kind": "other",
      "robotsTxtBlocked": false,
      "title": "Психолог для психолога | психолог Татьяна Мунн",
      "titleLength": 46,
      "description": "Психолог для психолога: материал Татьяны Мунн, психолога МГУ, о практической психологии, эмоциях, отношениях и саморегуляции.",
      "descriptionLength": 125,
      "canonical": "https://moonn.ru/psy4psy",
      "robots": "",
      "ogImagePresent": true,
      "h1Count": 1,
      "h1": [
        "ПСИХОЛОГ для ПСИХОЛОГОВ"
      ],
      "jsonLdCount": 0,
      "imageCount": 20,
      "imagesMissingAlt": 20,
      "issues": [
        "images_missing_alt",
        "missing_jsonld"
      ],
      "decision": "strengthen_seo"
    },
    {
      "url": "https://moonn.ru/psychoanalys",
      "lastmod": "",
      "status": 200,
      "contentType": "text/html; charset=UTF-8",
      "kind": "other",
      "robotsTxtBlocked": false,
      "title": "Психоанализ | психолог Татьяна Мунн",
      "titleLength": 35,
      "description": "Психоанализ: материал Татьяны Мунн, психолога МГУ, о практической психологии, эмоциях, отношениях и саморегуляции.",
      "descriptionLength": 114,
      "canonical": "https://moonn.ru/psychoanalys",
      "robots": "",
      "ogImagePresent": true,
      "h1Count": 1,
      "h1": [
        "Психоанализ"
      ],
      "jsonLdCount": 0,
      "imageCount": 4,
      "imagesMissingAlt": 4,
      "issues": [
        "images_missing_alt",
        "missing_jsonld"
      ],
      "decision": "strengthen_seo"
    },
    {
      "url": "https://moonn.ru/psypodgotovka1",
      "lastmod": "",
      "status": 200,
      "contentType": "text/html; charset=UTF-8",
      "kind": "other",
      "robotsTxtBlocked": false,
      "title": "Психологическая подготовка | психолог Татьяна Мунн",
      "titleLength": 50,
      "description": "Психологическая подготовка: материал Татьяны Мунн, психолога МГУ, о практической психологии, эмоциях, отношениях и саморегуляции.",
      "descriptionLength": 129,
      "canonical": "https://moonn.ru/psypodgotovka1",
      "robots": "",
      "ogImagePresent": true,
      "h1Count": 8,
      "h1": [
        "ПСИХОЛОГИЧЕСКАЯ подготовка к экзаменам (ОГЭ, ЕГЭ, Экзамены в ВУЗах)",
        "Как справиться со стрессом на экзаменах: Психологические стратегии для успеха",
        "Проверенные методы управления тревогой перед экзаменами"
      ],
      "jsonLdCount": 0,
      "imageCount": 22,
      "imagesMissingAlt": 20,
      "issues": [
        "images_missing_alt",
        "missing_jsonld",
        "multiple_h1"
      ],
      "decision": "strengthen_seo"
    },
    {
      "url": "https://moonn.ru/recomend",
      "lastmod": "",
      "status": 200,
      "contentType": "text/html; charset=UTF-8",
      "kind": "other",
      "robotsTxtBlocked": false,
      "title": "Рекомендации и материалы Татьяны Мунн | психолог Татьяна Мунн",
      "titleLength": 61,
      "description": "Рекомендации и материалы Татьяны Мунн: материал Татьяны Мунн, психолога МГУ, о практической психологии, эмоциях, отношениях и саморегуляции.",
      "descriptionLength": 140,
      "canonical": "https://moonn.ru/recomend",
      "robots": "",
      "ogImagePresent": true,
      "h1Count": 1,
      "h1": [
        "Полезная информация по ПСИХОЛОГИИ"
      ],
      "jsonLdCount": 0,
      "imageCount": 3,
      "imagesMissingAlt": 3,
      "issues": [
        "images_missing_alt",
        "missing_jsonld"
      ],
      "decision": "strengthen_seo"
    },
    {
      "url": "https://moonn.ru/salt",
      "lastmod": "",
      "status": 200,
      "contentType": "text/html; charset=UTF-8",
      "kind": "other",
      "robotsTxtBlocked": false,
      "title": "Соль и самочувствие | психолог Татьяна Мунн",
      "titleLength": 43,
      "description": "Соль и самочувствие: материал Татьяны Мунн, психолога МГУ, о практической психологии, эмоциях, отношениях и саморегуляции.",
      "descriptionLength": 122,
      "canonical": "https://moonn.ru/salt",
      "robots": "",
      "ogImagePresent": true,
      "h1Count": 0,
      "h1": [],
      "jsonLdCount": 0,
      "imageCount": 28,
      "imagesMissingAlt": 26,
      "issues": [
        "images_missing_alt",
        "missing_h1",
        "missing_jsonld"
      ],
      "decision": "strengthen_seo"
    },
    {
      "url": "https://moonn.ru/schematherapy",
      "lastmod": "",
      "status": 200,
      "contentType": "text/html; charset=UTF-8",
      "kind": "other",
      "robotsTxtBlocked": false,
      "title": "Схематерапия | психолог Татьяна Мунн",
      "titleLength": 36,
      "description": "Схематерапия: материал Татьяны Мунн, психолога МГУ, о практической психологии, эмоциях, отношениях и саморегуляции.",
      "descriptionLength": 115,
      "canonical": "https://moonn.ru/schematherapy",
      "robots": "",
      "ogImagePresent": true,
      "h1Count": 0,
      "h1": [],
      "jsonLdCount": 0,
      "imageCount": 3,
      "imagesMissingAlt": 3,
      "issues": [
        "images_missing_alt",
        "missing_h1",
        "missing_jsonld"
      ],
      "decision": "strengthen_seo"
    },
    {
      "url": "https://moonn.ru/selfharm",
      "lastmod": "",
      "status": 200,
      "contentType": "text/html; charset=UTF-8",
      "kind": "other",
      "robotsTxtBlocked": false,
      "title": "Самоповреждение у подростков | психолог Татьяна Мунн",
      "titleLength": 52,
      "description": "Самоповреждение у подростков: материал Татьяны Мунн, психолога МГУ, о практической психологии, эмоциях, отношениях и саморегуляции.",
      "descriptionLength": 131,
      "canonical": "https://moonn.ru/selfharm",
      "robots": "",
      "ogImagePresent": true,
      "h1Count": 0,
      "h1": [],
      "jsonLdCount": 0,
      "imageCount": 11,
      "imagesMissingAlt": 11,
      "issues": [
        "images_missing_alt",
        "missing_h1",
        "missing_jsonld"
      ],
      "decision": "strengthen_seo"
    },
    {
      "url": "https://moonn.ru/semeynie_konflikti_article",
      "lastmod": "",
      "status": 200,
      "contentType": "text/html; charset=UTF-8",
      "kind": "article",
      "robotsTxtBlocked": false,
      "title": "Семейные конфликты | Татьяна Мунн",
      "titleLength": 33,
      "description": "Семейные конфликты: авторская статья Татьяны Мунн, психолога МГУ, о поведении, эмоциях, отношениях и саморегуляции.",
      "descriptionLength": 115,
      "canonical": "https://moonn.ru/semeynie_konflikti_article",
      "robots": "",
      "ogImagePresent": true,
      "h1Count": 0,
      "h1": [],
      "jsonLdCount": 0,
      "imageCount": 2,
      "imagesMissingAlt": 2,
      "issues": [
        "images_missing_alt",
        "missing_h1",
        "missing_jsonld"
      ],
      "decision": "strengthen_seo"
    },
    {
      "url": "https://moonn.ru/semeyniy_psiholog",
      "lastmod": "",
      "status": 200,
      "contentType": "text/html; charset=UTF-8",
      "kind": "service",
      "robotsTxtBlocked": false,
      "title": "Семейный психолог: психолог МГУ Татьяна Мунн",
      "titleLength": 44,
      "description": "Семейный психолог: консультации Татьяны Мунн, психолога МГУ, в Москве и онлайн. Стресс, отношения, эмоции и личные состояния.",
      "descriptionLength": 125,
      "canonical": "https://moonn.ru/semeyniy_psiholog",
      "robots": "",
      "ogImagePresent": true,
      "h1Count": 0,
      "h1": [],
      "jsonLdCount": 0,
      "imageCount": 8,
      "imagesMissingAlt": 8,
      "issues": [
        "images_missing_alt",
        "missing_h1",
        "missing_jsonld"
      ],
      "decision": "strengthen_seo"
    },
    {
      "url": "https://moonn.ru/seminar555",
      "lastmod": "",
      "status": 200,
      "contentType": "text/html; charset=UTF-8",
      "kind": "other",
      "robotsTxtBlocked": false,
      "title": "Семинар по методу Быстрая психология | психолог Татьяна Мунн",
      "titleLength": 60,
      "description": "Семинар по методу Быстрая психология: материал Татьяны Мунн, психолога МГУ, о практической психологии, эмоциях, отношениях и саморегуляции.",
      "descriptionLength": 139,
      "canonical": "https://moonn.ru/seminar555",
      "robots": "",
      "ogImagePresent": true,
      "h1Count": 0,
      "h1": [],
      "jsonLdCount": 0,
      "imageCount": 31,
      "imagesMissingAlt": 31,
      "issues": [
        "images_missing_alt",
        "missing_h1",
        "missing_jsonld"
      ],
      "decision": "strengthen_seo"
    },
    {
      "url": "https://moonn.ru/shppp333",
      "lastmod": "",
      "status": 200,
      "contentType": "text/html; charset=UTF-8",
      "kind": "other",
      "robotsTxtBlocked": false,
      "title": "Школа практической психологии для подростков | психолог Татьяна Мунн",
      "titleLength": 68,
      "description": "Школа практической психологии для подростков: материал Татьяны Мунн, психолога МГУ, о практической психологии, эмоциях, отношениях и саморегуляции.",
      "descriptionLength": 147,
      "canonical": "https://moonn.ru/shppp333",
      "robots": "",
      "ogImagePresent": true,
      "h1Count": 1,
      "h1": [
        "Школа ПРАКТИЧЕСКОЙ Психологии для ПОДРОСТКОВ в г. Москве"
      ],
      "jsonLdCount": 0,
      "imageCount": 3,
      "imagesMissingAlt": 3,
      "issues": [
        "images_missing_alt",
        "missing_jsonld"
      ],
      "decision": "strengthen_seo"
    },
    {
      "url": "https://moonn.ru/speaker",
      "lastmod": "",
      "status": 200,
      "contentType": "text/html; charset=UTF-8",
      "kind": "lecture_or_events",
      "robotsTxtBlocked": false,
      "title": "Татьяна Мунн как спикер — психология и эмоциональный интеллект",
      "titleLength": 62,
      "description": "Татьяна Мунн как спикер: лекции и практические материалы Татьяны Мунн по психологии, эмоциональному интеллекту, отношениям и soft skills.",
      "descriptionLength": 137,
      "canonical": "https://moonn.ru/speaker",
      "robots": "",
      "ogImagePresent": true,
      "h1Count": 1,
      "h1": [
        "Татьяна Мунн - эксперт по эмоциональному интеллекту, soft skills и психологии состояний. Лекции, тренинги, корпоративные программы"
      ],
      "jsonLdCount": 0,
      "imageCount": 14,
      "imagesMissingAlt": 13,
      "issues": [
        "images_missing_alt",
        "missing_jsonld"
      ],
      "decision": "strengthen_seo"
    },
    {
      "url": "https://moonn.ru/st1",
      "lastmod": "",
      "status": 200,
      "contentType": "text/html; charset=UTF-8",
      "kind": "test_or_staging",
      "robotsTxtBlocked": false,
      "title": "онлайн-тренинг \"Среда Трансформации\". психолог Татьяна Мунн",
      "titleLength": 59,
      "description": "Гле взять силы и энергию на трансформацию и улучшения своей жизни? - Трансформационный тренинг ОНЛАЙН \"СРЕДА Трансформации\" поможет вернуть энергию и начать менять свою жизнь",
      "descriptionLength": 174,
      "canonical": "https://moonn.ru/st1",
      "robots": "",
      "ogImagePresent": true,
      "h1Count": 0,
      "h1": [],
      "jsonLdCount": 0,
      "imageCount": 9,
      "imagesMissingAlt": 9,
      "issues": [
        "duplicate_description",
        "images_missing_alt",
        "missing_h1",
        "missing_jsonld",
        "opaque_or_test_slug"
      ],
      "decision": "review_noindex_or_rename_slug"
    },
    {
      "url": "https://moonn.ru/st2",
      "lastmod": "",
      "status": 200,
      "contentType": "text/html; charset=UTF-8",
      "kind": "test_or_staging",
      "robotsTxtBlocked": false,
      "title": "онлайн-тренинг \"Среда Трансформации\" стартует 31 декабря 2025 года. Автор и ведущий психолог Татьяна Мунн",
      "titleLength": 105,
      "description": "Гле взять силы и энергию на трансформацию и улучшения своей жизни? - Трансформационный тренинг ОНЛАЙН \"СРЕДА Трансформации\" поможет вернуть энергию и начать менять свою жизнь",
      "descriptionLength": 174,
      "canonical": "https://moonn.ru/st2",
      "robots": "",
      "ogImagePresent": true,
      "h1Count": 0,
      "h1": [],
      "jsonLdCount": 0,
      "imageCount": 5,
      "imagesMissingAlt": 5,
      "issues": [
        "duplicate_description",
        "images_missing_alt",
        "long_title",
        "missing_h1",
        "missing_jsonld",
        "opaque_or_test_slug"
      ],
      "decision": "review_noindex_or_rename_slug"
    },
    {
      "url": "https://moonn.ru/trauma",
      "lastmod": "",
      "status": 200,
      "contentType": "text/html; charset=UTF-8",
      "kind": "other",
      "robotsTxtBlocked": false,
      "title": "Психологическая травма | психолог Татьяна Мунн",
      "titleLength": 46,
      "description": "Психологическая травма: материал Татьяны Мунн, психолога МГУ, о практической психологии, эмоциях, отношениях и саморегуляции.",
      "descriptionLength": 125,
      "canonical": "https://moonn.ru/trauma",
      "robots": "",
      "ogImagePresent": true,
      "h1Count": 1,
      "h1": [
        "Психология травмы:"
      ],
      "jsonLdCount": 0,
      "imageCount": 2,
      "imagesMissingAlt": 2,
      "issues": [
        "images_missing_alt",
        "missing_jsonld"
      ],
      "decision": "strengthen_seo"
    },
    {
      "url": "https://moonn.ru/uslugi_aerofobia",
      "lastmod": "",
      "status": 200,
      "contentType": "text/html; charset=UTF-8",
      "kind": "service",
      "robotsTxtBlocked": false,
      "title": "Аэрофобия Консультации по страху полётов (аэрофобия): психолог МГУ",
      "titleLength": 66,
      "description": "Аэрофобия Консультации по страху полётов (аэрофобия): консультации Татьяны Мунн, психолога МГУ, в Москве и онлайн. Стресс, отношения, эмоции и личные.",
      "descriptionLength": 150,
      "canonical": "https://moonn.ru/uslugi_aerofobia",
      "robots": "",
      "ogImagePresent": true,
      "h1Count": 6,
      "h1": [
        "Боишься летать на самолётах?",
        "Страх полетов на самолетах может проявляться у людей разных возрастов и социальных групп",
        "Просмотр телевизора и новостей может значительно влиять на формирование и усиление страха перед полетами на самолетах"
      ],
      "jsonLdCount": 0,
      "imageCount": 9,
      "imagesMissingAlt": 9,
      "issues": [
        "images_missing_alt",
        "missing_jsonld",
        "multiple_h1"
      ],
      "decision": "strengthen_seo"
    },
    {
      "url": "https://moonn.ru/uslugi_depression",
      "lastmod": "",
      "status": 200,
      "contentType": "text/html; charset=UTF-8",
      "kind": "service",
      "robotsTxtBlocked": false,
      "title": "Депрессивное состояние: понимание и преодоление: психолог МГУ",
      "titleLength": 61,
      "description": "Депрессивное состояние: понимание и преодоление: консультации Татьяны Мунн, психолога МГУ, в Москве и онлайн. Стресс, отношения, эмоции и личные состояния.",
      "descriptionLength": 155,
      "canonical": "https://moonn.ru/uslugi_depression",
      "robots": "",
      "ogImagePresent": true,
      "h1Count": 6,
      "h1": [
        "Депрессивное состояние:",
        "«Мне ничего не хочется»: симптомы депрессии",
        "Почему возникает депрессия?"
      ],
      "jsonLdCount": 0,
      "imageCount": 11,
      "imagesMissingAlt": 11,
      "issues": [
        "images_missing_alt",
        "missing_jsonld",
        "multiple_h1"
      ],
      "decision": "strengthen_seo"
    },
    {
      "url": "https://moonn.ru/uslugi_fin_blocks",
      "lastmod": "",
      "status": 200,
      "contentType": "text/html; charset=UTF-8",
      "kind": "service",
      "robotsTxtBlocked": false,
      "title": "Проработка финансовых блоков: психолог МГУ Татьяна Мунн",
      "titleLength": 55,
      "description": "Проработка финансовых блоков: консультации Татьяны Мунн, психолога МГУ, в Москве и онлайн. Стресс, отношения, эмоции и личные состояния.",
      "descriptionLength": 136,
      "canonical": "https://moonn.ru/uslugi_fin_blocks",
      "robots": "",
      "ogImagePresent": true,
      "h1Count": 1,
      "h1": [
        "Проработка финансовых блоков"
      ],
      "jsonLdCount": 0,
      "imageCount": 4,
      "imagesMissingAlt": 4,
      "issues": [
        "images_missing_alt",
        "missing_jsonld"
      ],
      "decision": "strengthen_seo"
    },
    {
      "url": "https://moonn.ru/uslugi_gtr",
      "lastmod": "",
      "status": 200,
      "contentType": "text/html; charset=UTF-8",
      "kind": "service",
      "robotsTxtBlocked": false,
      "title": "Тревожные расстройства: когда тревога становится болезнью: психолог",
      "titleLength": 67,
      "description": "Тревожные расстройства: когда тревога становится болезнью: консультации Татьяны Мунн, психолога МГУ, в Москве и онлайн. Стресс, отношения, эмоции и личные.",
      "descriptionLength": 155,
      "canonical": "https://moonn.ru/uslugi_gtr",
      "robots": "",
      "ogImagePresent": true,
      "h1Count": 7,
      "h1": [
        "Тревожные расстройства:",
        "Тревожное расстройство - что это?",
        "Ключевые признаки ГТР :"
      ],
      "jsonLdCount": 0,
      "imageCount": 14,
      "imagesMissingAlt": 14,
      "issues": [
        "images_missing_alt",
        "missing_jsonld",
        "multiple_h1"
      ],
      "decision": "strengthen_seo"
    },
    {
      "url": "https://moonn.ru/uslugi_konflikti_na_rabote",
      "lastmod": "",
      "status": 200,
      "contentType": "text/html; charset=UTF-8",
      "kind": "service",
      "robotsTxtBlocked": false,
      "title": "Проработка внутренних конфликтов, связанных с работой: психолог МГУ",
      "titleLength": 67,
      "description": "Проработка внутренних конфликтов, связанных с работой: консультации Татьяны Мунн, психолога МГУ, в Москве и онлайн. Стресс, отношения, эмоции и личные.",
      "descriptionLength": 151,
      "canonical": "https://moonn.ru/uslugi_konflikti_na_rabote",
      "robots": "",
      "ogImagePresent": true,
      "h1Count": 1,
      "h1": [
        "Проработка внутренних конфликтов, связанных с работой"
      ],
      "jsonLdCount": 0,
      "imageCount": 10,
      "imagesMissingAlt": 10,
      "issues": [
        "images_missing_alt",
        "missing_jsonld"
      ],
      "decision": "strengthen_seo"
    },
    {
      "url": "https://moonn.ru/uslugi_lubovnaya_zavisimost",
      "lastmod": "",
      "status": 200,
      "contentType": "text/html; charset=UTF-8",
      "kind": "service",
      "robotsTxtBlocked": false,
      "title": "Любовные зависимости и привязанности: психолог МГУ Татьяна Мунн",
      "titleLength": 63,
      "description": "Любовные зависимости и привязанности: консультации Татьяны Мунн, психолога МГУ, в Москве и онлайн. Стресс, отношения, эмоции и личные состояния.",
      "descriptionLength": 144,
      "canonical": "https://moonn.ru/uslugi_lubovnaya_zavisimost",
      "robots": "",
      "ogImagePresent": true,
      "h1Count": 6,
      "h1": [
        "Любовные зависимости и привязанности:",
        "Что такое любовная зависимость?",
        "Почему возникает любовная зависимость?"
      ],
      "jsonLdCount": 0,
      "imageCount": 8,
      "imagesMissingAlt": 8,
      "issues": [
        "images_missing_alt",
        "missing_jsonld",
        "multiple_h1"
      ],
      "decision": "strengthen_seo"
    },
    {
      "url": "https://moonn.ru/uslugi_obida_na_roditelei",
      "lastmod": "",
      "status": 200,
      "contentType": "text/html; charset=UTF-8",
      "kind": "service",
      "robotsTxtBlocked": false,
      "title": "Обида на родителей - негативные чувства, связанные с детством",
      "titleLength": 61,
      "description": "Обида на родителей - негативные чувства, связанные с детством: консультации Татьяны Мунн, психолога МГУ, в Москве и онлайн. Стресс, отношения, эмоции и.",
      "descriptionLength": 152,
      "canonical": "https://moonn.ru/uslugi_obida_na_roditelei",
      "robots": "",
      "ogImagePresent": true,
      "h1Count": 2,
      "h1": [
        "Обида на родителей:",
        "Обиды на родителей - причины"
      ],
      "jsonLdCount": 0,
      "imageCount": 6,
      "imagesMissingAlt": 6,
      "issues": [
        "images_missing_alt",
        "missing_jsonld",
        "multiple_h1"
      ],
      "decision": "strengthen_seo"
    },
    {
      "url": "https://moonn.ru/uslugi_otnosheniya_v_kollektive",
      "lastmod": "",
      "status": 200,
      "contentType": "text/html; charset=UTF-8",
      "kind": "service",
      "robotsTxtBlocked": false,
      "title": "Налаживание отношений в коллективе: психолог МГУ Татьяна Мунн",
      "titleLength": 61,
      "description": "Налаживание отношений в коллективе: консультации Татьяны Мунн, психолога МГУ, в Москве и онлайн. Стресс, отношения, эмоции и личные состояния.",
      "descriptionLength": 142,
      "canonical": "https://moonn.ru/uslugi_otnosheniya_v_kollektive",
      "robots": "",
      "ogImagePresent": true,
      "h1Count": 2,
      "h1": [
        "Налаживание отношений в коллективе",
        "Профилактика конфликтов:"
      ],
      "jsonLdCount": 0,
      "imageCount": 10,
      "imagesMissingAlt": 10,
      "issues": [
        "images_missing_alt",
        "missing_jsonld",
        "multiple_h1"
      ],
      "decision": "strengthen_seo"
    },
    {
      "url": "https://moonn.ru/uslugi_podrostki",
      "lastmod": "",
      "status": 200,
      "contentType": "text/html; charset=UTF-8",
      "kind": "service",
      "robotsTxtBlocked": false,
      "title": "Психологическая консультация для подростков от 12 лет: психолог МГУ",
      "titleLength": 67,
      "description": "Психологическая консультация для подростков от 12 лет: консультации Татьяны Мунн, психолога МГУ, в Москве и онлайн. Стресс, отношения, эмоции и личные.",
      "descriptionLength": 151,
      "canonical": "https://moonn.ru/uslugi_podrostki",
      "robots": "",
      "ogImagePresent": true,
      "h1Count": 1,
      "h1": [
        "Психологическая консультация для подростков от 12 лет"
      ],
      "jsonLdCount": 0,
      "imageCount": 10,
      "imagesMissingAlt": 10,
      "issues": [
        "images_missing_alt",
        "missing_jsonld"
      ],
      "decision": "strengthen_seo"
    },
    {
      "url": "https://moonn.ru/uslugi_procrastination",
      "lastmod": "",
      "status": 200,
      "contentType": "text/html; charset=UTF-8",
      "kind": "service",
      "robotsTxtBlocked": false,
      "title": "Прокрастинация: Почему мы откладываем дела на потом и как перестать",
      "titleLength": 67,
      "description": "Прокрастинация: Почему мы откладываем дела на потом и как перестать это: консультации Татьяны Мунн, психолога МГУ, в Москве и онлайн. Стресс, отношения.",
      "descriptionLength": 152,
      "canonical": "https://moonn.ru/uslugi_procrastination",
      "robots": "",
      "ogImagePresent": true,
      "h1Count": 6,
      "h1": [
        "Прокрастинация",
        "«Сделаю завтра»: Что такое прокрастинация?",
        "Почему мы откладываем дела?"
      ],
      "jsonLdCount": 0,
      "imageCount": 12,
      "imagesMissingAlt": 12,
      "issues": [
        "images_missing_alt",
        "missing_jsonld",
        "multiple_h1"
      ],
      "decision": "strengthen_seo"
    },
    {
      "url": "https://moonn.ru/uslugi_razvod",
      "lastmod": "",
      "status": 200,
      "contentType": "text/html; charset=UTF-8",
      "kind": "service",
      "robotsTxtBlocked": false,
      "title": "Помощь при расставании, измене, разводе: психолог МГУ Татьяна Мунн",
      "titleLength": 66,
      "description": "Помощь при расставании, измене, разводе: консультации Татьяны Мунн, психолога МГУ, в Москве и онлайн. Стресс, отношения, эмоции и личные состояния.",
      "descriptionLength": 147,
      "canonical": "https://moonn.ru/uslugi_razvod",
      "robots": "",
      "ogImagePresent": true,
      "h1Count": 3,
      "h1": [
        "Психологическая помощь при расставании, измене, разводе:",
        "Как пережить измену: восстановление доверия к себе и миру",
        "Когда обращаться к психологу?"
      ],
      "jsonLdCount": 0,
      "imageCount": 7,
      "imagesMissingAlt": 7,
      "issues": [
        "images_missing_alt",
        "missing_jsonld",
        "multiple_h1"
      ],
      "decision": "strengthen_seo"
    },
    {
      "url": "https://moonn.ru/uslugi_sohranit_brak",
      "lastmod": "",
      "status": 200,
      "contentType": "text/html; charset=UTF-8",
      "kind": "service",
      "robotsTxtBlocked": false,
      "title": "Как сохранить брак: преодоление кризисов, восстановление доверия и",
      "titleLength": 66,
      "description": "Как сохранить брак: преодоление кризисов, восстановление доверия и: консультации Татьяны Мунн, психолога МГУ, в Москве и онлайн. Стресс, отношения, эмоции и.",
      "descriptionLength": 157,
      "canonical": "https://moonn.ru/uslugi_sohranit_brak",
      "robots": "",
      "ogImagePresent": true,
      "h1Count": 5,
      "h1": [
        "Как сохранить брак",
        "Почему возникают кризисы в браке?",
        "Как научиться понимать партнера?"
      ],
      "jsonLdCount": 0,
      "imageCount": 9,
      "imagesMissingAlt": 9,
      "issues": [
        "images_missing_alt",
        "missing_jsonld",
        "multiple_h1"
      ],
      "decision": "strengthen_seo"
    },
    {
      "url": "https://moonn.ru/vacuum_cups",
      "lastmod": "",
      "status": 200,
      "contentType": "text/html; charset=UTF-8",
      "kind": "other",
      "robotsTxtBlocked": false,
      "title": "Вакуумные банки и самочувствие | психолог Татьяна Мунн",
      "titleLength": 54,
      "description": "Вакуумные банки и самочувствие: материал Татьяны Мунн, психолога МГУ, о практической психологии, эмоциях, отношениях и саморегуляции.",
      "descriptionLength": 133,
      "canonical": "https://moonn.ru/vacuum_cups",
      "robots": "",
      "ogImagePresent": true,
      "h1Count": 0,
      "h1": [],
      "jsonLdCount": 0,
      "imageCount": 26,
      "imagesMissingAlt": 26,
      "issues": [
        "images_missing_alt",
        "missing_h1",
        "missing_jsonld"
      ],
      "decision": "strengthen_seo"
    },
    {
      "url": "https://moonn.ru/vigoranie_article",
      "lastmod": "",
      "status": 200,
      "contentType": "text/html; charset=UTF-8",
      "kind": "article",
      "robotsTxtBlocked": false,
      "title": "Выгорание на работе | Татьяна Мунн",
      "titleLength": 34,
      "description": "Выгорание на работе: авторская статья Татьяны Мунн, психолога МГУ, о поведении, эмоциях, отношениях и саморегуляции.",
      "descriptionLength": 116,
      "canonical": "https://moonn.ru/vigoranie_article",
      "robots": "",
      "ogImagePresent": true,
      "h1Count": 1,
      "h1": [
        "Выгорание на работе"
      ],
      "jsonLdCount": 0,
      "imageCount": 10,
      "imagesMissingAlt": 10,
      "issues": [
        "images_missing_alt",
        "missing_jsonld"
      ],
      "decision": "strengthen_seo"
    },
    {
      "url": "https://moonn.ru/vospitanie_article",
      "lastmod": "",
      "status": 200,
      "contentType": "text/html; charset=UTF-8",
      "kind": "article",
      "robotsTxtBlocked": false,
      "title": "Воспитание ребенка | Татьяна Мунн",
      "titleLength": 33,
      "description": "Воспитание ребенка: авторская статья Татьяны Мунн, психолога МГУ, о поведении, эмоциях, отношениях и саморегуляции.",
      "descriptionLength": 115,
      "canonical": "https://moonn.ru/vospitanie_article",
      "robots": "",
      "ogImagePresent": true,
      "h1Count": 0,
      "h1": [],
      "jsonLdCount": 0,
      "imageCount": 2,
      "imagesMissingAlt": 2,
      "issues": [
        "images_missing_alt",
        "missing_h1",
        "missing_jsonld"
      ],
      "decision": "strengthen_seo"
    },
    {
      "url": "https://moonn.ru/vystupleniya-lekcii-treningi-psiholog-tatiana-moonn",
      "lastmod": "",
      "status": 200,
      "contentType": "text/html; charset=UTF-8",
      "kind": "lecture_or_events",
      "robotsTxtBlocked": false,
      "title": "Выступления, лекции и тренинги Татьяны Мунн — психология и",
      "titleLength": 58,
      "description": "Выступления, лекции и тренинги Татьяны Мунн: лекции и практические материалы Татьяны Мунн по психологии, эмоциональному интеллекту, отношениям и soft skills.",
      "descriptionLength": 157,
      "canonical": "https://moonn.ru/vystupleniya-lekcii-treningi-psiholog-tatiana-moonn",
      "robots": "",
      "ogImagePresent": true,
      "h1Count": 1,
      "h1": [
        "ТЕМЫ ЛЕКЦИЙ, КОТОРЫЕ Я ЧИТАЮ"
      ],
      "jsonLdCount": 0,
      "imageCount": 13,
      "imagesMissingAlt": 12,
      "issues": [
        "images_missing_alt",
        "missing_jsonld"
      ],
      "decision": "strengthen_seo"
    },
    {
      "url": "https://moonn.ru/water",
      "lastmod": "",
      "status": 200,
      "contentType": "text/html; charset=UTF-8",
      "kind": "other",
      "robotsTxtBlocked": false,
      "title": "Вода и психоэмоциональное состояние | психолог Татьяна Мунн",
      "titleLength": 59,
      "description": "Вода и психоэмоциональное состояние: материал Татьяны Мунн, психолога МГУ, о практической психологии, эмоциях, отношениях и саморегуляции.",
      "descriptionLength": 138,
      "canonical": "https://moonn.ru/water",
      "robots": "",
      "ogImagePresent": true,
      "h1Count": 1,
      "h1": [
        "Как правильно пить воду"
      ],
      "jsonLdCount": 0,
      "imageCount": 26,
      "imagesMissingAlt": 26,
      "issues": [
        "images_missing_alt",
        "missing_jsonld"
      ],
      "decision": "strengthen_seo"
    }
  ]
}